ner_util/__init__.py
ner_util/entity_list.py
ner_util/py.typed
ner_util-0.1.6.dist-info/METADATA
ner_util-0.1.6.dist-info/WHEEL
ner_util-0.1.6.dist-info/licenses/LICENSE
ner_util-0.1.6.dist-info/RECORD
