Metadata-Version: 2.4
Name: ner-util
Version: 0.1.6
Summary: Just another ner utils library
Author-email: Ceyda Cinarel <15624271+cceyda@users.noreply.github.com>
License-File: LICENSE
Requires-Python: >=3.9
